LICENSE.txt
MANIFEST.in
README.md
pyproject.toml
setup.cfg
src/notify_client_server/__init__.py
src/notify_client_server/admin_base.py
src/notify_client_server/cfg.py
src/notify_client_server/client.py
src/notify_client_server/os_specific.py
src/notify_client_server/server.py
src/notify_client_server/staging.py
src/notify_client_server/svc.py
src/notify_client_server/template_cfg.json
src/notify_client_server/template_notify_server.service
src/notify_client_server.egg-info/PKG-INFO
src/notify_client_server.egg-info/SOURCES.txt
src/notify_client_server.egg-info/dependency_links.txt
src/notify_client_server.egg-info/requires.txt
src/notify_client_server.egg-info/top_level.txt
src/notify_client_server/common/__init__.py
src/notify_client_server/common/constants.py
src/notify_client_server/common/constants_version.py