Metadata-Version: 2.4
Name: notify-client-server
Version: 0.1.9
Summary: notification server/website with client functions
Author-email: "J. Arrizza" <cppgent0@gmail.com>
Maintainer-email: "J. Arrizza" <cppgent0@gmail.com>
License-Expression: MIT
Project-URL: Website, https://arrizza.com/python-notify-client-server
Project-URL: Source, https://bitbucket.org/arrizza-public/notify-client-server/src/master
Project-URL: Download, https://bitbucket.org/arrizza-public/notify-client-server/get/master.zip
Keywords: notifications,client,server
Classifier: Development Status :: 4 - Beta
Classifier: Environment :: Console
Classifier: Topic :: Utilities
Classifier: Intended Audience :: Developers
Classifier: Programming Language :: Python :: 3.10
Classifier: Programming Language :: Python :: 3.12
Requires-Python: >=3.9
License-File: LICENSE.txt
Requires-Dist: requests
Requires-Dist: jsmin
Requires-Dist: falcon-logger
Dynamic: license-file
